setup.cfg
setup.py
seishub/__init__.py
seishub.plugins.seismology.egg-info/PKG-INFO
seishub.plugins.seismology.egg-info/SOURCES.txt
seishub.plugins.seismology.egg-info/dependency_links.txt
seishub.plugins.seismology.egg-info/entry_points.txt
seishub.plugins.seismology.egg-info/namespace_packages.txt
seishub.plugins.seismology.egg-info/not-zip-safe
seishub.plugins.seismology.egg-info/requires.txt
seishub.plugins.seismology.egg-info/top_level.txt
seishub/plugins/__init__.py
seishub/plugins/seismology/LICENSE.txt
seishub/plugins/seismology/README.txt
seishub/plugins/seismology/VERSION.txt
seishub/plugins/seismology/__init__.py
seishub/plugins/seismology/event.py
seishub/plugins/seismology/package.py
seishub/plugins/seismology/station.py
seishub/plugins/seismology/waveform.py
seishub/plugins/seismology/statics/seisgram/index.html
seishub/plugins/seismology/statics/seisgram/seis_view_n_04.js
seishub/plugins/seismology/statics/seisgram/java/SeisGram2K53.jar
seishub/plugins/seismology/templates/events.tmpl
seishub/plugins/seismology/templates/stations.tmpl
seishub/plugins/seismology/templates/waveforms.tmpl
seishub/plugins/seismology/xsd/xml-seed-1.1.xsd
seishub/plugins/seismology/xslt/event_googlemaps_xhtml.xslt
seishub/plugins/seismology/xslt/event_metadata.xslt
seishub/plugins/seismology/xslt/seiscomp2earthworm.xslt
seishub/plugins/seismology/xslt/station_googlemaps_xhtml.xslt
seishub/plugins/seismology/xslt/station_metadata.xslt