Metadata-Version: 1.0
Name: seishub.plugins.seismology
Version: 1.2.0
Summary: Seismology package for SeisHub.
Home-page: http://www.seishub.org
Author: Robert Barsch
Author-email: barsch@lmu.de
License: GNU Lesser General Public License, Version 3 (LGPLv3)
Download-URL: https://svn.geophysik.uni-muenchen.de/svn/seishub/trunk/seishub.plugins.seismology#egg=seishub.plugins.seismology-dev
Keywords: SeisHub,seismology
Platform: OS Independent
Classifier: Development Status :: 4 - Beta
Classifier: Environment :: Console
Classifier: Intended Audience :: Science/Research
Classifier: Intended Audience :: Developers
Classifier: License :: OSI Approved :: GNU Library or Lesser General Public License (LGPL)
Classifier: Operating System :: OS Independent
Classifier: Programming Language :: Python
Classifier: Topic :: Scientific/Engineering
Classifier: Topic :: Scientific/Engineering :: Physics
